fab_rk_tools/__init__.py
fab_rk_tools/assets/__init__.py
fab_rk_tools/assets/opt_plotly_theme.py
fab_rk_tools/assets/plotly_theme.py
fab_rk_tools/assets/plotly_theme_to_remove.py
fab_rk_tools/common/__init__.py
fab_rk_tools/common/constants.py
fab_rk_tools/common/utils.py
fab_rk_tools/data/__init__.py
fab_rk_tools/data/deriveddata.py
fab_rk_tools/data/test/__init__.py
fab_rk_tools/data/test/deriveddata_test.py
fab_rk_tools/exceptions/__init__.py
fab_rk_tools/exceptions/data.py
fab_rk_tools/graphs/__init__.py
fab_rk_tools/graphs/basic_bar.py
fab_rk_tools/graphs/discrete_distro_bar.py
fab_rk_tools/graphs/mirror_bar.py
fab_rk_tools/graphs/scatter_quantile_fan.py
fab_rk_tools/graphs/trafficlight_scatter.py
fab_rk_tools/stats/__init__.py
fab_rk_tools/stats/distribution.py
fab_rk_tools-0.3.17.dist-info/METADATA
fab_rk_tools-0.3.17.dist-info/WHEEL
fab_rk_tools-0.3.17.dist-info/RECORD
